{"cameraMode":{"drawMode":0,"name":"Shaded","section":"Shading Mode"},"sceneLighting":true,"audioPlay":false,"sceneViewState":{"showFog":true,"showMaterialUpdate":false,"showSkybox":true,"showFlares":true,"showImageEffects":true,"showParticleSystems":true},"in2DMode":false,"pivot":{"x":-0.9960566163063049,"y":-1.5360116958618165,"z":3.7174606323242189},"rotation":{"x":0.19707143306732179,"y":-0.11703211069107056,"z":0.023743294179439546,"w":0.973164439201355},"size":16.506948471069337,"orthographic":false}